apollo_ad/UI.py
apollo_ad/__init__.py
apollo_ad/apollo_ad.py
apollo_ad/demo.py
apollo_ad-0.0.7.dist-info/LICENSE
apollo_ad-0.0.7.dist-info/METADATA
apollo_ad-0.0.7.dist-info/WHEEL
apollo_ad-0.0.7.dist-info/top_level.txt
apollo_ad-0.0.7.dist-info/RECORD
