Metadata-Version: 2.1
Name: apollo-ad
Version: 0.0.7
Summary: Auto Differentiation Tools
Home-page: https://github.com/West-Coast-Quaranteam/cs107-FinalProject
Author: Connor Capitolo, Haoxin Li, Kexin Huang, Chen Zhang
Author-email: cosamhkx@gmail.com
License: MIT
Keywords: Auto-diff
Platform: UNKNOWN
Classifier: Development Status :: 3 - Alpha
Classifier: Intended Audience :: Developers
Classifier: Topic :: Software Development :: Build Tools
Classifier: License :: OSI Approved :: MIT License
Classifier: Programming Language :: Python :: 3
Classifier: Programming Language :: Python :: 3.4
Classifier: Programming Language :: Python :: 3.5
Classifier: Programming Language :: Python :: 3.6
Classifier: Programming Language :: Python :: 3.7
Classifier: Programming Language :: Python :: 3.8
Requires-Dist: numpy
Requires-Dist: pytest
